Metadata-Version: 1.0
Name: bintraypy_cli
Version: 0.1.0
Summary: Call (parts of) the Bintray API from the command-line
Home-page: http://github.com/Gohla/bintraypy_cli
Author: Gabriel Konat
Author-email: g.d.p.konat@tudelft.nl
License: Apache 2.0
Platform: UNKNOWN
